CHANGELOG.txt
LICENCE.txt
MANIFEST.in
README.txt
setup.py
pricelibrary/__init__.py
pricelibrary/booking_price.py
pricelibrary/models.py
pricelibrary.egg-info/PKG-INFO
pricelibrary.egg-info/SOURCES.txt
pricelibrary.egg-info/dependency_links.txt
pricelibrary.egg-info/requires.txt
pricelibrary.egg-info/top_level.txt