Metadata-Version: 2.1
Name: pricelibrary
Version: 0.0.1
Summary: Calculates and display the amount based on the duration
Home-page: 
Author: Stephen Angelo
Author-email: stephenangelo192@gmail.com
License: MIT
Keywords: calculation
Classifier: Development Status :: 5 - Production/Stable
Classifier: Intended Audience :: Education
Classifier: Operating System :: Microsoft :: Windows :: Windows 10
Classifier: License :: OSI Approved :: MIT License
Classifier: Programming Language :: Python :: 3
License-File: LICENCE.txt
